{"cameraMode":{"drawMode":0,"name":"Shaded","section":"Shading Mode"},"sceneLighting":true,"audioPlay":false,"sceneViewState":{"showFog":true,"showMaterialUpdate":false,"showSkybox":true,"showFlares":true,"showImageEffects":true,"showParticleSystems":true},"in2DMode":false,"pivot":{"x":2.8719096183776857,"y":12.626091003417969,"z":-3.291558265686035},"rotation":{"x":0.12866473197937013,"y":-0.0662684515118599,"z":0.009015090763568879,"w":0.9896904826164246},"size":11.140727996826172,"orthographic":false}